fema_p695/__init__.py
fema_p695/_version.py
fema_p695/farfield.hdf5
fema_p695/groundmotions.py
fema_p695/nearfield_no_pulse.hdf5
fema_p695/nearfield_pulse.hdf5
fema_p695-0.3.0.dist-info/LICENSE
fema_p695-0.3.0.dist-info/METADATA
fema_p695-0.3.0.dist-info/WHEEL
fema_p695-0.3.0.dist-info/top_level.txt
fema_p695-0.3.0.dist-info/RECORD
